{
  "$schema": "https://raw.githubusercontent.com/vramework/vramework/refs/heads/master/packages/cli/cli.schema.json",
  "tsconfig": "./tsconfig.json",
  "routeDirectories": [
    "packages/functions/src"
  ],
  "outDir": "packages/functions/.vramework",
  "routesMapDeclarationFile": "packages/sdk/.vramework/routes-map.d.ts",
  "channelsMapDeclarationFile": "packages/sdk/.vramework/channels-map.d.ts",
  "fetchFile": "packages/sdk/.vramework/vramework-fetch.ts",
  "websocketFile": "packages/sdk/.vramework/vramework-websocket.ts",
  "packageMappings": {
    "packages/sdk": "@vramework-workspace-starter/sdk",
    "packages/functions": "@vramework-workspace-starter/functions"
  },
  "openAPI": {
    "outputFile": "openapi.yml",
    "additionalInfo": {
      "info": {
        "title": "Vramework Workspace Starter API",
        "version": "1.0.0",
        "description": "This is the openapi spec for the Vramework Workspace Starter API"
      },
      "servers": [
        {
          "url": "http://localhost:4002",
          "description": "Development server"
        }
      ]
    }
  }
}